LICENSE.txt
MANIFEST.in
README.txt
setup.cfg
setup.py
gzutils/__init__.py
gzutils/gzutils.py
gzutils.egg-info/PKG-INFO
gzutils.egg-info/SOURCES.txt
gzutils.egg-info/dependency_links.txt
gzutils.egg-info/top_level.txt