Metadata-Version: 1.1
Name: gzutils
Version: 0.0.5
Summary: Gizur misc utils
Home-page: https://github.com/gizur/gzutils.py
Author: Jonas Colmsjö
Author-email: jonas.colmsjo@gizur.com
License: MIT
Keywords: utils logging cvs dotdict
Platform: UNKNOWN
Classifier: Development Status :: 3 - Alpha
Classifier: Intended Audience :: Developers
Classifier: Topic :: Software Development :: Libraries :: Python Modules
Classifier: License :: OSI Approved :: MIT License
Classifier: Programming Language :: Python :: 3
